ai_term/__init__.py
ai_term/cli/__init__.py
ai_term/cli/config.py
ai_term/cli/main.py
ai_term/cli/core/__init__.py
ai_term/cli/core/agent.py
ai_term/cli/core/audio_client.py
ai_term/cli/core/audio_player.py
ai_term/cli/core/audio_recorder.py
ai_term/cli/core/mcp_manager.py
ai_term/cli/db/__init__.py
ai_term/cli/db/engine.py
ai_term/cli/db/models.py
ai_term/cli/resources/__init__.py
ai_term/cli/resources/docker-compose.yml
ai_term/cli/ui/__init__.py
ai_term/cli/ui/app.py
ai_term/cli/ui/constants.py
ai_term/cli/ui/styles.tcss
ai_term/cli/ui/screens/__init__.py
ai_term/cli/ui/screens/chat.py
ai_term/cli/ui/screens/confirmation.py
ai_term/cli/ui/screens/help.py
ai_term/cli/ui/screens/settings.py
ai_term/cli/ui/widgets/__init__.py
ai_term/cli/ui/widgets/input_area.py
ai_term/cli/ui/widgets/message.py
ai_term/cli/ui/widgets/sidebar.py
ai_term/cli/ui/widgets/status_bar.py
ai_term/cli/ui/widgets/thinking_indicator.py
ai_term/common/__init__.py
ai_term/common/model_manager.py
ai_term/stt/Dockerfile
ai_term/stt/__init__.py
ai_term/stt/main.py
ai_term/tts/Dockerfile
ai_term/tts/__init__.py
ai_term/tts/interface.py
ai_term/tts/main.py
ai_term/tts/providers/__init__.py
ai_term/tts/providers/coqui.py
ai_term/tts/providers/elevenlabs.py
py_aiterm-0.0.1.dist-info/METADATA
py_aiterm-0.0.1.dist-info/WHEEL
py_aiterm-0.0.1.dist-info/entry_points.txt
py_aiterm-0.0.1.dist-info/licenses/LICENSE
py_aiterm-0.0.1.dist-info/RECORD
