Metadata-Version: 2.4
Name: py-aiterm
Version: 0.0.1
Summary: A modern, voice-enabled AI terminal assistant with local LLM integration and Model Context Protocol (MCP) support.
Project-URL: Repository, https://github.com/vsaravind01/ai-term.git
Author-email: Sudharsan Aravind <vsaravind01@gmail.com>
License-Expression: MIT
License-File: LICENSE
Keywords: ai,assistant,llm,mcp,speech-to-text,terminal,text-to-speech,textual,voice
Classifier: Development Status :: 4 - Beta
Classifier: Environment :: Console
Classifier: Intended Audience :: Developers
Classifier: Programming Language :: Python :: 3.10
Classifier: Programming Language :: Python :: 3.11
Requires-Python: >=3.10
Requires-Dist: aiosqlite>=0.20.0
Requires-Dist: httpx>=0.27.0
Requires-Dist: langchain-ollama>=0.2.0
Requires-Dist: langchain>=0.3.0
Requires-Dist: mcp>=1.0.0
Requires-Dist: pydantic-settings>=2.0.0
Requires-Dist: python-dotenv>=1.2.1
Requires-Dist: sounddevice>=0.5.3
Requires-Dist: sqlalchemy[asyncio]>=2.0.0
Requires-Dist: textual>=0.80.0
Requires-Dist: typer>=0.21.0
Provides-Extra: dev
Requires-Dist: pytest-asyncio>=0.24.0; extra == 'dev'
Requires-Dist: pytest-cov>=6.0.0; extra == 'dev'
Requires-Dist: pytest-mock>=3.14.0; extra == 'dev'
Requires-Dist: pytest>=8.0.0; extra == 'dev'
Requires-Dist: ruff>=0.1.0; extra == 'dev'
Requires-Dist: textual-dev>=0.80.0; extra == 'dev'
Provides-Extra: docs
Requires-Dist: mkdocs-material>=9.5.0; extra == 'docs'
Requires-Dist: mkdocs-mermaid2-plugin>=1.1.0; extra == 'docs'
Requires-Dist: mkdocs>=1.6.0; extra == 'docs'
Requires-Dist: mkdocstrings[python]>=0.25.0; extra == 'docs'
Provides-Extra: server
Requires-Dist: fastapi>=0.112.0; extra == 'server'
Requires-Dist: python-multipart>=0.0.9; extra == 'server'
Requires-Dist: uvicorn>=0.30.0; extra == 'server'
Provides-Extra: stt
Requires-Dist: ai-term[server]; extra == 'stt'
Requires-Dist: openai-whisper>=20250625; extra == 'stt'
Provides-Extra: tts
Requires-Dist: ai-term[server]; extra == 'tts'
Requires-Dist: tts>=0.22.0; extra == 'tts'
